clarity_common/__init__.py
clarity_common/models/__init__.py
clarity_common/models/common_models/__init__.py
clarity_common/models/common_models/models.py
clarity_common-1.0.40.dist-info/METADATA
clarity_common-1.0.40.dist-info/WHEEL
clarity_common-1.0.40.dist-info/RECORD
